{"tool_name":"4sale","contents":["biotools","bioschemas"],"fetched_metadata":{"biotools":{"id":"4sale","home":"http://4sale.bioapps.biozentrum.uni-wuerzburg.de/index.html","summary":"4SALE allows a fast sequence and synchronous secondary structure alignment for large data sets and for the first time synchronous manual editing of aligned sequences and their secondary structures. This study describes an algorithm for the synchronous alignment of sequences and their associated secondary structures as well as the main features of 4SALE used for further analyses and editing. 4SALE builds an optimal and unique starting point for every RNA sequence and structure analysis.","addition_date":"2017-12-18T00:03:06Z","last_update_date":"2018-12-10T12:58:51Z","tool_type":["Desktop application"],"version":["1.7"]},"bioschemas":{"name":"4SALE","home":"https://bio.tools/4sale","version":"1.7","summary":"4SALE allows a fast sequence and synchronous secondary structure alignment for large data sets and for the first time synchronous manual editing of aligned sequences and their secondary structures. This study describes an algorithm for the synchronous alignment of sequences and their associated secondary structures as well as the main features of 4SALE used for further analyses and editing. 4SALE builds an optimal and unique starting point for every RNA sequence and structure analysis.","tool_type":"sc:SoftwareApplication"}}}