{"tool_name":"a-o-tool","contents":["biotools","bioschemas"],"fetched_metadata":{"biotools":{"id":"a-o-tool","home":"https://github.com/Julia-F-S/a-o-tool","license":"GPL-3.0","summary":"Exploiting orthology and de novo transcriptome assembly to refine target sequence information.","addition_date":"2019-08-09T13:20:26Z","last_update_date":"2020-06-16T10:55:25Z","tool_type":["Command-line tool"]},"bioschemas":{"name":"a-o-tool","home":"https://bio.tools/a-o-tool","license":"GPL-3.0","summary":"Exploiting orthology and de novo transcriptome assembly to refine target sequence information.","tool_type":"sc:SoftwareApplication"}}}