{"tool_name":"acgh","contents":["biotools","bioschemas","bioconda"],"fetched_metadata":{"bioconda":{"name":"bioconductor-acgh","version":"1.84.0","home":"https://bioconductor.org/packages/3.20/bioc/html/aCGH.html","license":"GPL-2","summary":"Classes and functions for Array Comparative Genomic Hybridization data","identifiers":["biotools:acgh","doi:10.1093/bioinformatics/bti677"]},"biotools":{"id":"acgh","home":"http://bioconductor.org/packages/release/bioc/html/aCGH.html","license":"GPL-2.0","summary":"This tool includes functions for reading aCGH data from image analysis output files and clone information files or creating S3 objects for storing these data. It also incudes basic methods for accessing/replacing, subsetting, printing and plotting aCGH objects.","addition_date":"2017-01-17T15:00:54Z","last_update_date":"2024-11-25T15:24:20.167264Z","tool_type":["Command-line tool","Library"],"version":["1.52.0"],"collections":["BioConductor"]},"bioschemas":{"name":"aCGH","home":"https://bio.tools/acgh","license":"GPL-2.0","version":"1.52.0","summary":"This tool includes functions for reading aCGH data from image analysis output files and clone information files or creating S3 objects for storing these data. It also incudes basic methods for accessing/replacing, subsetting, printing and plotting aCGH objects.","tool_type":"sc:SoftwareApplication"}}}