{"tool_name":"badmedicine","contents":["biotools","bioschemas"],"fetched_metadata":{"biotools":{"id":"badmedicine","home":"https://github.com/HicServices/BadMedicine","license":"GPL-3.0","summary":"Library and command-line tool for generating realistic-looking synthetic Electronic Health Records (EHR) data for testing purposes; optional plugin BadMedicine.Dicom for extending this to generating DICOM files.","addition_date":"2020-07-28T15:21:56Z","last_update_date":"2021-04-14T19:49:54Z","tool_type":["Library"]},"bioschemas":{"name":"BadMedicine","home":"https://bio.tools/badmedicine","license":"GPL-3.0","summary":"Library and command-line tool for generating realistic-looking synthetic Electronic Health Records (EHR) data for testing purposes; optional plugin BadMedicine.Dicom for extending this to generating DICOM files.","tool_type":"sc:SoftwareApplication"}}}