{"tool_name":"biosurfdb","contents":["biotools","bioschemas"],"fetched_metadata":{"biotools":{"id":"biosurfdb","home":"https://www.biosurfdb.org","summary":"BioSurfDB is a online database for biodegradation and biosurfactants.","addition_date":"2025-04-29T17:07:56.642694Z","last_update_date":"2025-04-29T17:35:41.655075Z","tool_type":["Database portal"]},"bioschemas":{"name":"BioSurfDB","home":"https://bio.tools/biosurfdb","summary":"BioSurfDB is a online database for biodegradation and biosurfactants.","tool_type":"sc:SoftwareApplication"}}}