{"tool_name":"bonita","contents":["biotools","bioschemas"],"fetched_metadata":{"biotools":{"id":"BONITA","home":"https://github.com/thakar-lab/BONITA","summary":"Executable pathway analysis using ensemble discrete-state modeling for large-scale data | BONITA- Boolean Omics Network Invariant-Time Analysis is a package for the inference of Boolean rules and pathway analysis on omics data. It can be applied to help uncover underlying relationships in biological data. Please see our publication for more information: [insert eventual publication here]","addition_date":"2019-11-14T19:38:33Z","last_update_date":"2020-12-09T15:00:37Z"},"bioschemas":{"name":"BONITA","home":"https://bio.tools/BONITA","summary":"Executable pathway analysis using ensemble discrete-state modeling for large-scale data | BONITA- Boolean Omics Network Invariant-Time Analysis is a package for the inference of Boolean rules and pathway analysis on omics data. It can be applied to help uncover underlying relationships in biological data. Please see our publication for more information: [insert eventual publication here]","tool_type":"sc:SoftwareApplication"}}}