{"tool_name":"bpm-matlab","contents":["biotools","bioschemas"],"fetched_metadata":{"biotools":{"id":"bpm-matlab","home":"https://gitlab.gbar.dtu.dk/biophotonics/BPM-Matlab","license":"GPL-3.0","summary":"BPM-Matlab is a numerical simulation tool to efficiently model electric field propagation in a wide variety of optical fiber geometries with arbitrary refractive index profiles even in the presence of bending.","addition_date":"2021-06-14T13:30:17Z","last_update_date":"2021-08-18T09:41:22Z","tool_type":["Script"]},"bioschemas":{"name":"BPM-Matlab","home":"https://bio.tools/bpm-matlab","license":"GPL-3.0","summary":"BPM-Matlab is a numerical simulation tool to efficiently model electric field propagation in a wide variety of optical fiber geometries with arbitrary refractive index profiles even in the presence of bending.","tool_type":"sc:SoftwareApplication"}}}