{"tool_name":"brainwiki","contents":["biotools","bioschemas"],"fetched_metadata":{"biotools":{"id":"brainwiki","home":"http://Brainwiki.org","summary":"BrainWiki is a Wiki-Style, User Driven, Comparative Brain Anatomy Tool.","addition_date":"2021-01-18T12:06:31Z","last_update_date":"2021-02-06T16:50:13Z"},"bioschemas":{"name":"BrainWiki","home":"https://bio.tools/brainwiki","summary":"BrainWiki is a Wiki-Style, User Driven, Comparative Brain Anatomy Tool.","tool_type":"sc:SoftwareApplication"}}}