{"tool_name":"bwa-sw","contents":["biotools","bioschemas"],"fetched_metadata":{"biotools":{"id":"bwa-sw","home":"http://bio-bwa.sourceforge.net/","license":"MIT","summary":"Fast, accurate, memory-efficient aligner for long sequencing reads","addition_date":"2017-01-13T13:13:56Z","last_update_date":"2021-04-15T19:26:38Z","tool_type":["Command-line tool"],"collections":["BWA"]},"bioschemas":{"name":"BWA-SW","home":"https://bio.tools/bwa-sw","license":"MIT","summary":"Fast, accurate, memory-efficient aligner for long sequencing reads","tool_type":"sc:SoftwareApplication"}}}