{"tool_name":"bwimage","contents":["biotools","bioschemas"],"fetched_metadata":{"biotools":{"id":"bwimage","home":"https://cran.r-project.org/web/packages/bwimage/index.html","license":"GPL-2.0","summary":"A package to describe image patterns in natural structures.\n\nDescribe Image Patterns in Natural Structures.\n\nA computational tool to describe patterns in black and white images from natural structures. 'bwimage' implemented functions for exceptionally broad subject. For instance, 'bwimage' provide examples that range from calculation of canopy openness, description of patterns in vertical vegetation structure, to patterns in bird nest structure.\n\nThe facility to obtain high quality digital images creates the opportunity to measure natural variables using image analyses. Bwimage is an R package to analyze patterns in black and white images from natural structures.\n\nA computational tool to describe patterns from black and white images","addition_date":"2020-01-09T17:51:59Z","last_update_date":"2020-12-09T15:55:31Z"},"bioschemas":{"name":"bwimage","home":"https://bio.tools/bwimage","license":"GPL-2.0","summary":"A package to describe image patterns in natural structures.\n\nDescribe Image Patterns in Natural Structures.\n\nA computational tool to describe patterns in black and white images from natural structures. 'bwimage' implemented functions for exceptionally broad subject. For instance, 'bwimage' provide examples that range from calculation of canopy openness, description of patterns in vertical vegetation structure, to patterns in bird nest structure.\n\nThe facility to obtain high quality digital images creates the opportunity to measure natural variables using image analyses. Bwimage is an R package to analyze patterns in black and white images from natural structures.\n\nA computational tool to describe patterns from black and white images","tool_type":"sc:SoftwareApplication"}}}