{"tool_name":"cider","contents":["biotools","bioschemas"],"fetched_metadata":{"biotools":{"id":"cider","home":"http://pappulab.wustl.edu/CIDER/","summary":"Classification of Intrinsically Disordered Ensemble Regions.","addition_date":"2018-08-07T09:38:15Z","last_update_date":"2018-12-10T12:59:01Z","tool_type":["Web application"]},"bioschemas":{"name":"CIDER","home":"https://bio.tools/cider","summary":"Classification of Intrinsically Disordered Ensemble Regions.","tool_type":"sc:SoftwareApplication"}}}