{"tool_name":"cra_toolbox","contents":["biotools","bioschemas"],"fetched_metadata":{"biotools":{"id":"CRA_toolbox","home":"http://gitlab.ict4life.com/SysBiOThe/CRA-Matlab","summary":"Software package for conditional robustness analysis of cancer systems biology models in MATLAB.","addition_date":"2019-07-13T13:33:20Z","last_update_date":"2024-11-24T21:03:18.854515Z","tool_type":["Desktop application"]},"bioschemas":{"name":"CRA toolbox","home":"https://bio.tools/CRA_toolbox","summary":"Software package for conditional robustness analysis of cancer systems biology models in MATLAB.","tool_type":"sc:SoftwareApplication"}}}