{"tool_name":"ctag","contents":["biotools","bioschemas"],"fetched_metadata":{"biotools":{"id":"ctag","home":"https://github.com/RamanLab/cTaG","summary":"cTaG (classify TSG and OG) is a tool used to identify tumour suppressor genes (TSGs) and oncogenes (OGs) using somatic mutation data.","addition_date":"2022-06-11T11:16:34.194462Z","last_update_date":"2022-06-11T11:16:34.197101Z","tool_type":["Workflow"]},"bioschemas":{"name":"cTaG","home":"https://bio.tools/ctag","summary":"cTaG (classify TSG and OG) is a tool used to identify tumour suppressor genes (TSGs) and oncogenes (OGs) using somatic mutation data.","tool_type":"sc:SoftwareApplication"}}}