{"tool_name":"ctdpathsim","contents":["biotools","bioschemas"],"fetched_metadata":{"biotools":{"id":"ctdpathsim","home":"https://github.com/bozdaglab/CTDPathSim","license":"CC-BY-NC-4.0","summary":"The R package CTDPathSim is a computational pipeline to compute similarity scores between patient samples and cell lines using a pathway activity-based approach. CTDPathSim integrates sample-specific expression and methylation profiles utilizing a deconvolution method. CTDPathSim has four main computational steps.","addition_date":"2021-01-18T09:37:21Z","last_update_date":"2021-02-18T18:07:14Z","tool_type":["Library","Workflow"]},"bioschemas":{"name":"CTDPathSim","home":"https://bio.tools/ctdpathsim","license":"CC-BY-NC-4.0","summary":"The R package CTDPathSim is a computational pipeline to compute similarity scores between patient samples and cell lines using a pathway activity-based approach. CTDPathSim integrates sample-specific expression and methylation profiles utilizing a deconvolution method. CTDPathSim has four main computational steps.","tool_type":"sc:SoftwareApplication"}}}