{"tool_name":"dar","contents":["biotools","bioschemas"],"fetched_metadata":{"biotools":{"id":"dar","home":"https://dar.biocomp.unibo.it/","license":"CC-BY-NC-4.0","summary":"DAR is a database mapping disease-associated enzyme into Reactome pathways.","addition_date":"2024-03-08T09:21:03.040121Z","last_update_date":"2024-11-24T14:10:46.700720Z","tool_type":["Database portal"],"collections":["Bologna Biocomputing Group"]},"bioschemas":{"name":"DAR","home":"https://bio.tools/dar","license":"CC-BY-NC-4.0","summary":"DAR is a database mapping disease-associated enzyme into Reactome pathways.","tool_type":"sc:SoftwareApplication"}}}