{"tool_name":"decode-framework","contents":["biotools","bioschemas"],"fetched_metadata":{"biotools":{"id":"decode-framework","home":"http://decode.gersteinlab.org","summary":"A Deep-learning Framework for Condensing Enhancers and Refining Boundaries with Large-scale Functional Assays.","addition_date":"2021-03-19T08:46:25Z","last_update_date":"2021-03-22T16:28:04Z","tool_type":["Workbench"]},"bioschemas":{"name":"DECODE","home":"https://bio.tools/decode-framework","summary":"A Deep-learning Framework for Condensing Enhancers and Refining Boundaries with Large-scale Functional Assays.","tool_type":"sc:SoftwareApplication"}}}