{"tool_name":"deepdlncud","contents":["biotools","bioschemas"],"fetched_metadata":{"biotools":{"id":"deepdlncud","home":"https://github.com/2003100127/deepdlncud","summary":"Predicting regulation types of small molecule inhibitors on modulating lncRNA expression by deep learning.","addition_date":"2024-01-30T15:44:10.920337Z","last_update_date":"2024-11-24T14:18:02.959207Z","tool_type":["Library"]},"bioschemas":{"name":"DeepdlncUD","home":"https://bio.tools/deepdlncud","summary":"Predicting regulation types of small molecule inhibitors on modulating lncRNA expression by deep learning.","tool_type":"sc:SoftwareApplication"}}}