{"tool_name":"eso","contents":["biotools","bioschemas"],"fetched_metadata":{"biotools":{"id":"eso","home":"https://www.cs.tau.ac.il/~tamirtul/ESO/","summary":"A Novel Approach to Identify and Avoid Mutational Hotspots in DNA Sequences While Maintaining High Expression Levels.","addition_date":"2022-06-07T17:19:01.987395Z","last_update_date":"2024-11-24T20:08:46.441973Z","tool_type":["Desktop application"]},"bioschemas":{"name":"ESO","home":"https://bio.tools/eso","summary":"A Novel Approach to Identify and Avoid Mutational Hotspots in DNA Sequences While Maintaining High Expression Levels.","tool_type":"sc:SoftwareApplication"}}}