{"tool_name":"extramapper","contents":["biotools","bioschemas"],"fetched_metadata":{"biotools":{"id":"extramapper","home":"http://ay-lab-tools.lji.org/extramapper","license":"MIT","summary":"ExTraMapper is a tool to find Exon and Transcript-level Mappings of a given pair of orthologous genes between two organisms using sequence conservation.","addition_date":"2021-09-08T16:27:23Z","last_update_date":"2024-11-24T20:19:26.025045Z","tool_type":["Database portal"]},"bioschemas":{"name":"ExTraMapper","home":"https://bio.tools/extramapper","license":"MIT","summary":"ExTraMapper is a tool to find Exon and Transcript-level Mappings of a given pair of orthologous genes between two organisms using sequence conservation.","tool_type":"sc:SoftwareApplication"}}}