{"tool_name":"fiberq","contents":["biotools","bioschemas"],"fetched_metadata":{"biotools":{"id":"fiberq","home":"https://www.mathworks.com/matlabcentral/fileexchange/69788-fiberq","summary":"FiberQ is a MATLAB script for automatic quantification of dna fibers from fluorescent images","addition_date":"2021-05-05T10:50:03Z","last_update_date":"2024-11-24T20:25:56.888635Z","tool_type":["Library"],"version":["1.0.0"],"collections":["File Exchange","MATLAB"]},"bioschemas":{"name":"FiberQ","home":"https://bio.tools/fiberq","version":"1.0.0","summary":"FiberQ is a MATLAB script for automatic quantification of dna fibers from fluorescent images","tool_type":"sc:SoftwareApplication"}}}