{"tool_name":"fox-insight","contents":["biotools","bioschemas"],"fetched_metadata":{"biotools":{"id":"fox-insight","home":"https://foxden.michaeljfox.org/","summary":"Fox Insight Collects Online, Longitudinal Patient-Reported Outcomes and Genetic Data on Parkinson's Disease | Fox DEN provides investigators with a tool to explore, download and apply statistical models on aggregated data collected for the Fox Insight online clinical study. The Fox Insight study collects patient-reported outcomes and genetic data from people with Parkinson's disease and their loved ones","addition_date":"2019-11-14T18:33:57Z","last_update_date":"2020-12-29T11:17:31Z","tool_type":["Web application"]},"bioschemas":{"name":"Fox Insight","home":"https://bio.tools/fox-insight","summary":"Fox Insight Collects Online, Longitudinal Patient-Reported Outcomes and Genetic Data on Parkinson's Disease | Fox DEN provides investigators with a tool to explore, download and apply statistical models on aggregated data collected for the Fox Insight online clinical study. The Fox Insight study collects patient-reported outcomes and genetic data from people with Parkinson's disease and their loved ones","tool_type":"sc:SoftwareApplication"}}}