{"tool_name":"fromgtftobed12","contents":["galaxy"],"fetched_metadata":{"galaxy":{"version":"0.11.1+galaxy1","first_commit":"2019-07-31","conda_name":"gffutils","conda_version":"0.13","summary":"Convert GTF files to BED12 format","edam_operations":[],"edam_topics":[],"toolshed_categories":["Convert Formats"],"toolshed_id":"fromgtftobed12","users_5_years":0,"users_all_time":0,"usage_5_years":0,"usage_all_time":0,"related_tutorials":[],"related_workflows":[],"tool_ids":["fromgtfTobed12"],"no_of_tools":{"eu":0,"org":0,"org.au":0,"be":0,"cz":0,"fr":0,"no":0}}}}