{"tool_name":"gems","contents":["biotools","bioschemas"],"fetched_metadata":{"biotools":{"id":"gems","home":"http://genomics10.bu.edu/terrence/gems/","summary":"Tool for biclustering microarray data.  It is available as a web tool and as a standalone command-line program.","addition_date":"2017-02-10T14:16:02Z","last_update_date":"2024-11-25T15:01:19.252459Z","tool_type":["Web application"]},"bioschemas":{"name":"GEMS","home":"https://bio.tools/gems","summary":"Tool for biclustering microarray data.  It is available as a web tool and as a standalone command-line program.","tool_type":"sc:SoftwareApplication"}}}