{"tool_name":"ichromo","contents":["biotools","bioschemas"],"fetched_metadata":{"biotools":{"id":"ichromo","home":"https://chromo.cloud","license":"Not licensed","summary":"Application for Unsupervised Analysis of Chromosome Movements in Meiosis.","addition_date":"2022-01-19T22:53:44.687824Z","last_update_date":"2022-02-16T14:08:36.024052Z","tool_type":["Web application"]},"bioschemas":{"name":"ChroMo","home":"https://bio.tools/ichromo","license":"Not licensed","summary":"Application for Unsupervised Analysis of Chromosome Movements in Meiosis.","tool_type":"sc:SoftwareApplication"}}}