{"tool_name":"immunocluster","contents":["biotools","bioschemas"],"fetched_metadata":{"biotools":{"id":"immunocluster","home":"https://github.com/kordastilab/ImmunoCluster","license":"MIT","summary":"A computational framework for the non-specialist to profile cellular heterogeneity in cytometry datasets.\n\nThe immunoCluster package uses the scDataViz bioconductor package\u2019s vizualization tools and adaptation of the SingleCellExperiment data structure to build simple and flexible cytometry analysis workflows like those outlined in Nowicka et al. (2017) CyTOF workflow: differential discovery in high-throughput high-dimensional cytometry datasets.","addition_date":"2021-01-18T10:43:32Z","last_update_date":"2021-09-27T08:00:49.714594Z","tool_type":["Library"]},"bioschemas":{"name":"ImmunoCluster","home":"https://bio.tools/immunocluster","license":"MIT","summary":"A computational framework for the non-specialist to profile cellular heterogeneity in cytometry datasets.\n\nThe immunoCluster package uses the scDataViz bioconductor package\u2019s vizualization tools and adaptation of the SingleCellExperiment data structure to build simple and flexible cytometry analysis workflows like those outlined in Nowicka et al. (2017) CyTOF workflow: differential discovery in high-throughput high-dimensional cytometry datasets.","tool_type":"sc:SoftwareApplication"}}}