{"tool_name":"interactivecomplexheatmap","contents":["biotools","bioschemas"],"fetched_metadata":{"biotools":{"id":"interactivecomplexheatmap","home":"https://bioconductor.org/packages/InteractiveComplexHeatmap/","license":"MIT","summary":"InteractiveComplexHeatmap is a R package to make make heatmaps which are produced by the ComplexHeatmap package into interactive applications.","addition_date":"2021-09-25T19:52:53.757848Z","last_update_date":"2021-09-28T18:19:08.458974Z","tool_type":["Library"]},"bioschemas":{"name":"InteractiveComplexHeatmap","home":"https://bio.tools/interactivecomplexheatmap","license":"MIT","summary":"InteractiveComplexHeatmap is a R package to make make heatmaps which are produced by the ComplexHeatmap package into interactive applications.","tool_type":"sc:SoftwareApplication"}}}