{"tool_name":"iodata","contents":["biotools","bioschemas"],"fetched_metadata":{"biotools":{"id":"iodata","home":"https://github.com/theochem/iodata","license":"LGPL-3.0","summary":"A python library for reading, writing, and converting computational chemistry file formats and generating input files.\n\nIOData is a HORTON 3 module for input/output of quantum chemistry file formats. Documentation is here: https://iodata.readthedocs.io/en/latest/index.html.","addition_date":"2021-01-18T12:19:01Z","last_update_date":"2021-02-05T07:40:36Z","tool_type":["Command-line tool"]},"bioschemas":{"name":"IOData","home":"https://bio.tools/iodata","license":"LGPL-3.0","summary":"A python library for reading, writing, and converting computational chemistry file formats and generating input files.\n\nIOData is a HORTON 3 module for input/output of quantum chemistry file formats. Documentation is here: https://iodata.readthedocs.io/en/latest/index.html.","tool_type":"sc:SoftwareApplication"}}}