{"tool_name":"itis-psetnc","contents":["biotools","bioschemas"],"fetched_metadata":{"biotools":{"id":"itis-psetnc","home":"http://lin.uestc.edu.cn/server/iTIS-PseTNC","summary":"This web-server was developed to identify Translation initiation site (TIS) by using the physicochemical properties of the pseudo trinucleotide composition.","addition_date":"2017-08-03T19:06:19Z","last_update_date":"2024-11-25T16:14:31.826432Z","tool_type":["Web application"]},"bioschemas":{"name":"iTIS-PseTNC","home":"https://bio.tools/itis-psetnc","summary":"This web-server was developed to identify Translation initiation site (TIS) by using the physicochemical properties of the pseudo trinucleotide composition.","tool_type":"sc:SoftwareApplication"}}}