{"tool_name":"ito","contents":["biotools","bioschemas"],"fetched_metadata":{"biotools":{"id":"ito","home":"https://openbiolink.github.io/ITOExplorer/","license":"MIT","summary":"A curated, ontology-based, large-scale knowledge graph of artificial intelligence tasks and benchmarks.","addition_date":"2022-09-07T22:24:49.807763Z","last_update_date":"2022-09-07T22:24:49.811269Z","tool_type":["Web application"]},"bioschemas":{"name":"ITO","home":"https://bio.tools/ito","license":"MIT","summary":"A curated, ontology-based, large-scale knowledge graph of artificial intelligence tasks and benchmarks.","tool_type":"sc:SoftwareApplication"}}}