{"tool_name":"kernel_canonical_correlation_analysis","contents":["galaxy"],"fetched_metadata":{"galaxy":{"version":"1.0.0","first_commit":"2014-05-19","conda_name":"rpy","summary":"Kernel Canonical Correlation Analysis","edam_operations":[],"edam_topics":[],"toolshed_categories":["Statistics"],"toolshed_id":"kernel_canonical_correlation_analysis","users_5_years":37,"users_all_time":82,"usage_5_years":232,"usage_all_time":422,"related_tutorials":[],"related_workflows":[],"tool_ids":["kcca1"],"no_of_tools":{"eu":1,"org":1,"org.au":0,"be":1,"cz":1,"fr":1,"no":1}}}}