{"tool_name":"libra","contents":["biotools","bioschemas"],"fetched_metadata":{"biotools":{"id":"libra","home":"http://tools.proteomecenter.org/Libra.php","summary":"Analyzes 4- and 8-channel iTRAQ data.","addition_date":"2017-01-17T14:51:34Z","last_update_date":"2024-11-25T14:14:35.065133Z","tool_type":["Command-line tool","Desktop application"],"collections":["Proteomics","ms-utils"]},"bioschemas":{"name":"Libra","home":"https://bio.tools/libra","summary":"Analyzes 4- and 8-channel iTRAQ data.","tool_type":"sc:SoftwareApplication"}}}