{"tool_name":"luca","contents":["biotools","bioschemas"],"fetched_metadata":{"biotools":{"id":"luca","home":"http://stat.sfu.ca/statgen/research/luca.html","summary":"R package implementing the methods for case-control inference of statistical interaction between genetic and nongenetic risk factors under covariate assumptions.","addition_date":"2017-08-03T18:48:18Z","last_update_date":"2024-11-25T15:21:40.527507Z","tool_type":["Library"]},"bioschemas":{"name":"LUCA","home":"https://bio.tools/luca","summary":"R package implementing the methods for case-control inference of statistical interaction between genetic and nongenetic risk factors under covariate assumptions.","tool_type":"sc:SoftwareApplication"}}}