{"tool_name":"mflink","contents":["biotools"],"fetched_metadata":{"biotools":{"id":"mflink","home":"http://www.davecurtis.net/dcurtis/software.html","summary":"Simple program which automates setting up likelihood calculations for linkage analysis using a variety of different transmission models, and then collating the results in order to produce a (nearly) model free lod score.","addition_date":"2017-08-03T18:49:22Z","last_update_date":"2024-11-25T15:52:51.315147Z","tool_type":["Command-line tool"]}}}