{"tool_name":"mirror","contents":["biotools","bioschemas"],"fetched_metadata":{"biotools":{"id":"mirror","home":"http://mirror.egnome.co.kr/","license":"MIT","summary":"Database and Tool for Metataxonomics with Long-Read Sequence.","addition_date":"2022-06-28T18:28:36.611862Z","last_update_date":"2022-06-28T18:28:36.614365Z","tool_type":["Database portal","Web application"]},"bioschemas":{"name":"MIrROR","home":"https://bio.tools/mirror","license":"MIT","summary":"Database and Tool for Metataxonomics with Long-Read Sequence.","tool_type":"sc:SoftwareApplication"}}}