{"tool_name":"miscnn","contents":["biotools","bioschemas"],"fetched_metadata":{"biotools":{"id":"miscnn","home":"https://github.com/frankkramer-lab/MIScnn","license":"GPL-3.0","summary":"A framework for medical image segmentation with convolutional neural networks and deep learning.\n\nThe open-source Python library MIScnn is an intuitive API allowing fast setup of medical image segmentation pipelines with state-of-the-art convolutional neural network and deep learning models in just a few lines of code.","addition_date":"2021-03-19T08:29:46Z","last_update_date":"2021-04-11T09:28:07Z","tool_type":["Command-line tool"]},"bioschemas":{"name":"MIScnn","home":"https://bio.tools/miscnn","license":"GPL-3.0","summary":"A framework for medical image segmentation with convolutional neural networks and deep learning.\n\nThe open-source Python library MIScnn is an intuitive API allowing fast setup of medical image segmentation pipelines with state-of-the-art convolutional neural network and deep learning models in just a few lines of code.","tool_type":"sc:SoftwareApplication"}}}