{"tool_name":"mitoannotator","contents":["biotools","bioschemas"],"fetched_metadata":{"biotools":{"id":"mitoannotator","home":"https://mitofish.aori.u-tokyo.ac.jp/annotation/input/","license":"CC-BY-NC-3.0","summary":"MitoAnnotator is a pipeline for annotating fish mitogenomic sequence fully automatically and accurately just in 30 seconds.","addition_date":"2025-06-16T15:26:37.851391Z","last_update_date":"2025-06-16T15:37:19.175954Z","tool_type":["Bioinformatics portal"]},"bioschemas":{"name":"MitoAnnotator","home":"https://bio.tools/mitoannotator","license":"CC-BY-NC-3.0","summary":"MitoAnnotator is a pipeline for annotating fish mitogenomic sequence fully automatically and accurately just in 30 seconds.","tool_type":"sc:SoftwareApplication"}}}