{"tool_name":"mmp","contents":["biotools","bioschemas"],"fetched_metadata":{"biotools":{"id":"mmp","home":"https://sfb.mmp2.sigma2.no","license":"CC-BY-ND-3.0","summary":"The Marine Metagenomics Portal (MMP) hosts the marine databases MarRef, MarDB, MarFun, and SalDB. These databases provide the marine scientific community with openly accessible, comprehensive microbial genomics and metagenomics resources, including high-quality, manually curated sequences. The user-friendly web interface allows visitors to easily navigate and refine searches within the contextual databases and offers additional BLAST searches, visualizations, downloads, and workflows (via META-pipe).","addition_date":"2018-01-16T22:02:06Z","last_update_date":"2025-01-17T09:29:45.738020Z","tool_type":["Database portal"],"collections":["ELIXIR-NO","ELIXIR-Norway","Marine Metagenomics Portal","UiT"]},"bioschemas":{"name":"Marine Metagenomics Portal","home":"https://bio.tools/mmp","license":"CC-BY-ND-3.0","summary":"The Marine Metagenomics Portal (MMP) hosts the marine databases MarRef, MarDB, MarFun, and SalDB. These databases provide the marine scientific community with openly accessible, comprehensive microbial genomics and metagenomics resources, including high-quality, manually curated sequences. The user-friendly web interface allows visitors to easily navigate and refine searches within the contextual databases and offers additional BLAST searches, visualizations, downloads, and workflows (via META-pipe).","tool_type":"sc:SoftwareApplication"}}}