{"tool_name":"mrireco","contents":["biotools","bioschemas"],"fetched_metadata":{"biotools":{"id":"mrireco","home":"https://github.com/MagneticResonanceImaging/MRIReco.jl","license":"MIT","summary":"MRIReco is a Julia packet for magnetic resonance imaging. It contains algorithms for the simulation and reconstruction of MRT data and is both easy to use and flexibly expandable.","addition_date":"2021-10-11T08:15:39.877133Z","last_update_date":"2021-10-11T08:16:39.639522Z","tool_type":["Workflow"]},"bioschemas":{"name":"MRIReco","home":"https://bio.tools/mrireco","license":"MIT","summary":"MRIReco is a Julia packet for magnetic resonance imaging. It contains algorithms for the simulation and reconstruction of MRT data and is both easy to use and flexibly expandable.","tool_type":"sc:SoftwareApplication"}}}