{"tool_name":"mrpixel","contents":["biotools","bioschemas"],"fetched_metadata":{"biotools":{"id":"mrpixel","home":"http://www.crystal.chem.ed.ac.uk/software/mrpixel","summary":"Automated execution of Pixel calculations via the Mercury interface.\n\nMrPIXEL is a program that enables the energetics of crystal packing to be analysed quickly and easy through a user interface, using PIXEL, Python scripts and the widely known visualiser, Mercury.","addition_date":"2021-01-18T10:38:18Z","last_update_date":"2021-03-01T09:41:19Z","tool_type":["Desktop application","Script"]},"bioschemas":{"name":"MrPIXEL","home":"https://bio.tools/mrpixel","summary":"Automated execution of Pixel calculations via the Mercury interface.\n\nMrPIXEL is a program that enables the energetics of crystal packing to be analysed quickly and easy through a user interface, using PIXEL, Python scripts and the widely known visualiser, Mercury.","tool_type":"sc:SoftwareApplication"}}}