{"tool_name":"nanocross","contents":["biotools","bioschemas"],"fetched_metadata":{"biotools":{"id":"nanocross","home":"https://github.com/zuoquanchen/NanoCross","license":"Other","summary":"A pipeline that detecting recombinant crossover using ONT sequencing data.","addition_date":"2022-11-15T08:03:53.759689Z","last_update_date":"2024-11-24T15:21:06.347936Z","tool_type":["Script","Workflow"]},"bioschemas":{"name":"NanoCross","home":"https://bio.tools/nanocross","license":"Other","summary":"A pipeline that detecting recombinant crossover using ONT sequencing data.","tool_type":"sc:SoftwareApplication"}}}