{"tool_name":"neat-genreads","contents":["biotools","bioschemas"],"fetched_metadata":{"biotools":{"id":"neat-genreads","home":"https://github.com/zstephens/neat-genreads","license":"GPL-3.0","summary":"A fine-grained read simulator. GenReads simulates real-looking data using models learned from specific datasets. There are several supporting utilities for generating models used for simulation.","addition_date":"2017-08-20T15:58:17Z","last_update_date":"2024-11-25T14:05:14.537171Z","tool_type":["Command-line tool"],"collections":["Animal and Crop Genomics"]},"bioschemas":{"name":"NEAT-genreads","home":"https://bio.tools/neat-genreads","license":"GPL-3.0","summary":"A fine-grained read simulator. GenReads simulates real-looking data using models learned from specific datasets. There are several supporting utilities for generating models used for simulation.","tool_type":"sc:SoftwareApplication"}}}