{"tool_name":"neuro-current_response_functions","contents":["biotools","bioschemas"],"fetched_metadata":{"biotools":{"id":"Neuro-Current_Response_Functions","home":"https://github.com/proloyd/neuro-currentRF","license":"BSD-2-Clause","summary":"A Unified Approach to MEG Source Analysis under the Continuous Stimuli Paradigm | The magnetoencephalography (MEG) response to continuous auditory stimuli, such as speech, is commonly described using a linear filter, the auditory temporal response function (TRF) | This repository contains the implementation of our direct TRF estimation algorithm in python (version 3.6 and above)","addition_date":"2019-11-14T20:06:24Z","last_update_date":"2021-01-04T07:58:45Z","tool_type":["Command-line tool"]},"bioschemas":{"name":"Neuro-Current Response Functions","home":"https://bio.tools/Neuro-Current_Response_Functions","license":"BSD-2-Clause","summary":"A Unified Approach to MEG Source Analysis under the Continuous Stimuli Paradigm | The magnetoencephalography (MEG) response to continuous auditory stimuli, such as speech, is commonly described using a linear filter, the auditory temporal response function (TRF) | This repository contains the implementation of our direct TRF estimation algorithm in python (version 3.6 and above)","tool_type":"sc:SoftwareApplication"}}}