{"tool_name":"openxgr","contents":["biotools","bioschemas"],"fetched_metadata":{"biotools":{"id":"openxgr","home":"http://www.openxgr.com","license":"GPL-3.0","summary":"Web-server update for genomic summary data interpretation.","addition_date":"2023-12-20T23:31:43.280005Z","last_update_date":"2024-11-24T14:27:29.415259Z","tool_type":["Web application"]},"bioschemas":{"name":"OpenXGR","home":"https://bio.tools/openxgr","license":"GPL-3.0","summary":"Web-server update for genomic summary data interpretation.","tool_type":"sc:SoftwareApplication"}}}