{"tool_name":"pca-pam50","contents":["biotools","bioschemas"],"fetched_metadata":{"biotools":{"id":"PCA-PAM50","home":"ftp://ftp.wriwindber.org/","license":"GPL-3.0","summary":"Principle Component Analysis-based iterative PAM50 subtyping (PCA-PAM50) improves consistency between breast cancer intrinsic and clinical subtyping reclassifying a subset of luminal A tumors as luminal B.","addition_date":"2019-08-09T13:14:27Z","last_update_date":"2020-06-16T10:55:26Z","tool_type":["Library"]},"bioschemas":{"name":"PCA-PAM50","home":"https://bio.tools/PCA-PAM50","license":"GPL-3.0","summary":"Principle Component Analysis-based iterative PAM50 subtyping (PCA-PAM50) improves consistency between breast cancer intrinsic and clinical subtyping reclassifying a subset of luminal A tumors as luminal B.","tool_type":"sc:SoftwareApplication"}}}