{"tool_name":"pcmdb_pancreatic_cancer_methylation_database","contents":["biotools","bioschemas"],"fetched_metadata":{"biotools":{"id":"pcmdb_pancreatic_cancer_methylation_database","home":"https://webs.iiitd.edu.in/raghava/pcmdb/index.php","summary":"PCMdb is a database of methylated genes found in pancreatic cancer cell lines and tissues.","addition_date":"2022-10-10T06:09:59.089908Z","last_update_date":"2022-10-10T06:10:07.114471Z","tool_type":["Web application"]},"bioschemas":{"name":"pcmdb :  Pancreatic Cancer Methylation Database","home":"https://bio.tools/pcmdb_pancreatic_cancer_methylation_database","summary":"PCMdb is a database of methylated genes found in pancreatic cancer cell lines and tissues.","tool_type":"sc:SoftwareApplication"}}}