{"tool_name":"per_viewer","contents":["biotools","bioschemas"],"fetched_metadata":{"biotools":{"id":"PER_viewer","home":"http://per.broadinstitute.org","license":"Unlicense","summary":"Identification of pathogenic variant enriched regions across genes and gene families.","addition_date":"2019-08-09T13:24:01Z","last_update_date":"2020-06-16T10:55:26Z","tool_type":["Web application"]},"bioschemas":{"name":"PER viewer","home":"https://bio.tools/PER_viewer","license":"Unlicense","summary":"Identification of pathogenic variant enriched regions across genes and gene families.","tool_type":"sc:SoftwareApplication"}}}