{"tool_name":"pint_pathways","contents":["biotools","bioschemas"],"fetched_metadata":{"biotools":{"id":"pint_pathways","home":"http://csb2.ym.edu.tw/pint/","summary":"Pathway INtegration Tool (PINT) allows integration and annotation of systems biology markup language (SBML) files from a variety of sources. Gene list files are also accepted.","addition_date":"2017-05-01T13:39:27Z","last_update_date":"2024-11-25T14:59:20.828022Z","tool_type":["Web application"]},"bioschemas":{"name":"PINT","home":"https://bio.tools/pint_pathways","summary":"Pathway INtegration Tool (PINT) allows integration and annotation of systems biology markup language (SBML) files from a variety of sources. Gene list files are also accepted.","tool_type":"sc:SoftwareApplication"}}}