{"tool_name":"potato","contents":["biotools","bioschemas"],"fetched_metadata":{"biotools":{"id":"potato","home":"https://github.com/REMI-HIRI/POTATO","license":"GPL-3.0","summary":"An automated pipeline for batch analysis of optical tweezers data.","addition_date":"2022-04-03T21:29:38.795415Z","last_update_date":"2022-04-03T21:29:38.797851Z","tool_type":["Script"]},"bioschemas":{"name":"POTATO","home":"https://bio.tools/potato","license":"GPL-3.0","summary":"An automated pipeline for batch analysis of optical tweezers data.","tool_type":"sc:SoftwareApplication"}}}