{"tool_name":"projective_transformation","contents":["galaxy"],"fetched_metadata":{"galaxy":{"version":"0.1.2","first_commit":"2018-12-07","conda_name":"scikit-image","summary":"Projective transformation","edam_operations":["Image analysis"],"edam_topics":["Imaging","Bioinformatics"],"toolshed_categories":["Imaging"],"toolshed_id":"projective_transformation","users_5_years":4,"users_all_time":6,"usage_5_years":33,"usage_all_time":86,"bio_tools_summary":"Galaxy Image Analysis is mainly developed by the Biomedical Computer Vision (BMCV) Group at Heidelberg University. Its dedication is to provide tools for image analysis and image processing for the Galaxy platform.","bio_tools_ids":"galaxy_image_analysis","bio_tools_name":"Galaxy Image Analysis","related_tutorials":[],"related_workflows":[{"create_time":"2021-01-02","latest_version":19,"link":"https://usegalaxy.eu/published/workflow?id=1eaff95bfeb13890","name":"Registration of images based on landmarks"}],"tool_ids":["ip_projective_transformation"],"no_of_tools":{"eu":1,"org":0,"org.au":0,"be":0,"cz":1,"fr":0,"no":1}}}}