{"tool_name":"rmsa","contents":["biotools","bioschemas"],"fetched_metadata":{"biotools":{"id":"rmsa","home":"https://zhanggroup.org/rMSA/","summary":"Sequence search and alignment algorithm to improve RNA structure modeling.","addition_date":"2024-01-26T11:49:55.400849Z","last_update_date":"2024-11-24T14:19:35.146101Z","tool_type":["Web application"]},"bioschemas":{"name":"rMSA","home":"https://bio.tools/rmsa","summary":"Sequence search and alignment algorithm to improve RNA structure modeling.","tool_type":"sc:SoftwareApplication"}}}