{"tool_name":"scagecom","contents":["biotools","bioschemas"],"fetched_metadata":{"biotools":{"id":"scagecom","home":"https://scagecom.org","license":"MIT","summary":"A murine atlas of age-related changes in intercellular communication inferred with the package scDiffCom.","addition_date":"2021-12-14T12:22:43.461509Z","last_update_date":"2021-12-14T12:22:43.464540Z","tool_type":["Library","Web application"]},"bioschemas":{"name":"scAgeCom","home":"https://bio.tools/scagecom","license":"MIT","summary":"A murine atlas of age-related changes in intercellular communication inferred with the package scDiffCom.","tool_type":"sc:SoftwareApplication"}}}