{"tool_name":"sczewas","contents":["biotools","bioschemas"],"fetched_metadata":{"biotools":{"id":"sczewas","home":"https://github.com/ejh243/SCZEWAS","license":"GPL-2.0","summary":"Analysis of co-localization of genetic associations and differential DNA methylation.","addition_date":"2018-08-12T10:32:19Z","last_update_date":"2024-11-25T14:28:23.386147Z","tool_type":["Library"]},"bioschemas":{"name":"SCZEWAS","home":"https://bio.tools/sczewas","license":"GPL-2.0","summary":"Analysis of co-localization of genetic associations and differential DNA methylation.","tool_type":"sc:SoftwareApplication"}}}