{"tool_name":"sdmtoolbox","contents":["biotools","bioschemas"],"fetched_metadata":{"biotools":{"id":"sdmtoolbox","home":"http://sdmtoolbox.org/","summary":"Next generation Python-based GIS toolkit for landscape genetic, biogeographic and species distribution model analyses.","addition_date":"2018-07-28T13:32:27Z","last_update_date":"2018-12-10T12:59:00Z","tool_type":["Desktop application"],"version":["2.0"]},"bioschemas":{"name":"SDMtoolbox","home":"https://bio.tools/sdmtoolbox","version":"2.0","summary":"Next generation Python-based GIS toolkit for landscape genetic, biogeographic and species distribution model analyses.","tool_type":"sc:SoftwareApplication"}}}