{"tool_name":"speedygenesxl","contents":["biotools","bioschemas"],"fetched_metadata":{"biotools":{"id":"speedygenesxl","home":"https://github.com/neilswainston/SpeedyGenesXL","license":"Not licensed","summary":"An Automated, High-Throughput Platform for the Preparation of Bespoke Ultralarge Variant Libraries for Directed Evolution.","addition_date":"2022-09-01T12:26:39.322597Z","last_update_date":"2024-11-24T15:44:41.444776Z","tool_type":["Command-line tool"]},"bioschemas":{"name":"SpeedyGenesXL","home":"https://bio.tools/speedygenesxl","license":"Not licensed","summary":"An Automated, High-Throughput Platform for the Preparation of Bespoke Ultralarge Variant Libraries for Directed Evolution.","tool_type":"sc:SoftwareApplication"}}}