{"tool_name":"structurly","contents":["biotools","bioschemas"],"fetched_metadata":{"biotools":{"id":"structurly","home":"https://nicocriscuolo.shinyapps.io/StructuRly/","license":"GPL-2.0","summary":"A novel shiny app to produce comprehensive, detailed and interactive plots for population genetic analysis.\n\nStructuRly is an R package containing a shiny application to produce detailed and interactive graphs of the results of a Bayesian cluster analysis obtained with the most common population genetic software used to investigate population structure, such as STRUCTURE or ADMIXTURE.","addition_date":"2021-01-18T07:37:45Z","last_update_date":"2021-02-24T10:49:35Z"},"bioschemas":{"name":"StructuRly","home":"https://bio.tools/structurly","license":"GPL-2.0","summary":"A novel shiny app to produce comprehensive, detailed and interactive plots for population genetic analysis.\n\nStructuRly is an R package containing a shiny application to produce detailed and interactive graphs of the results of a Bayesian cluster analysis obtained with the most common population genetic software used to investigate population structure, such as STRUCTURE or ADMIXTURE.","tool_type":"sc:SoftwareApplication"}}}