{"tool_name":"sylarray","contents":["biotools","bioschemas"],"fetched_metadata":{"biotools":{"id":"sylarray","home":"http://www.ebi.ac.uk/enright-srv/sylarray/","summary":"Examine influence of small RNAs on expression profiles.","addition_date":"2015-01-29T15:47:03Z","last_update_date":"2024-11-24T15:21:47.742043Z","tool_type":["Web application"],"version":["Retired"],"collections":["EBI Tools"]},"bioschemas":{"name":"Sylarray","home":"https://bio.tools/sylarray","version":"Retired","summary":"Examine influence of small RNAs on expression profiles.","tool_type":"sc:SoftwareApplication"}}}