{"tool_name":"targetrna","contents":["biotools","bioschemas"],"fetched_metadata":{"biotools":{"id":"targetrna","home":"http://cs.wellesley.edu/~btjaden/TargetRNA2/","summary":"TargetRNA is a web based tool for identifying mRNA targets of small non-coding RNAs in bacterial species.","addition_date":"2017-03-24T14:34:27Z","last_update_date":"2024-11-25T15:04:13.036199Z","tool_type":["Web application"]},"bioschemas":{"name":"TargetRNA","home":"https://bio.tools/targetrna","summary":"TargetRNA is a web based tool for identifying mRNA targets of small non-coding RNAs in bacterial species.","tool_type":"sc:SoftwareApplication"}}}