{"tool_name":"trap-seq","contents":["biotools","bioschemas"],"fetched_metadata":{"biotools":{"id":"trap-seq","home":"https://github.com/TerminatorJ/CRISPR-TRAP-seq.git","license":"MIT","summary":"Massively parallel quantification of CRISPR editing in cells by TRAP-seq enables better design of Cas9, ABE, CBE gRNAs of high efficiency and accuracy.","addition_date":"2021-01-18T09:19:38Z","last_update_date":"2021-03-03T10:52:01Z"},"bioschemas":{"name":"TRAP-seq","home":"https://bio.tools/trap-seq","license":"MIT","summary":"Massively parallel quantification of CRISPR editing in cells by TRAP-seq enables better design of Cas9, ABE, CBE gRNAs of high efficiency and accuracy.","tool_type":"sc:SoftwareApplication"}}}