{"tool_name":"tvar","contents":["biotools","bioschemas"],"fetched_metadata":{"biotools":{"id":"tvar","home":"https://github.com/haiyang1986/TVAR","license":"Not licensed","summary":"Assessing Tissue-specific Functional Effects of Non-coding Variants with Deep Learning.","addition_date":"2022-10-28T07:46:14.230357Z","last_update_date":"2024-11-24T15:25:32.485838Z","tool_type":["Command-line tool"]},"bioschemas":{"name":"TVAR","home":"https://bio.tools/tvar","license":"Not licensed","summary":"Assessing Tissue-specific Functional Effects of Non-coding Variants with Deep Learning.","tool_type":"sc:SoftwareApplication"}}}