{"tool_name":"ubibrowser_2.0","contents":["biotools","bioschemas"],"fetched_metadata":{"biotools":{"id":"ubibrowser_2.0","home":"http://ubibrowser.ncpsb.org.cn","summary":"A comprehensive resource for proteome-wide known and predicted ubiquitin ligase/deubiquitinase-substrate interactions in eukaryotic species.","addition_date":"2022-03-09T22:41:51.457132Z","last_update_date":"2022-03-09T22:41:51.460049Z","tool_type":["Database portal","Web application"]},"bioschemas":{"name":"UbiBrowser 2.0","home":"https://bio.tools/ubibrowser_2.0","summary":"A comprehensive resource for proteome-wide known and predicted ubiquitin ligase/deubiquitinase-substrate interactions in eukaryotic species.","tool_type":"sc:SoftwareApplication"}}}