{"tool_name":"ucarechemsuitecli","contents":["biotools","bioschemas"],"fetched_metadata":{"biotools":{"id":"ucarechemsuitecli","home":"https://sauravsaha.shinyapps.io/ucarechemsuite2/","license":"MIT","summary":"This suite of packages is developed to predicts resistome for unknown chemical compounds. It utilizes two algorithms viz. deterministic model and stochastic model (manuscript under preparation) for the prediction of drug class. Once the drug class is predicted, the resistome profile of Escherichia coli and Pseudomonas aeruginosa for the drug class is fetched from the database.","addition_date":"2021-11-15T16:57:32.511353Z","last_update_date":"2021-11-15T16:57:32.513926Z","tool_type":["Web application"]},"bioschemas":{"name":"uCAREChemSuiteCLI","home":"https://bio.tools/ucarechemsuitecli","license":"MIT","summary":"This suite of packages is developed to predicts resistome for unknown chemical compounds. It utilizes two algorithms viz. deterministic model and stochastic model (manuscript under preparation) for the prediction of drug class. Once the drug class is predicted, the resistome profile of Escherichia coli and Pseudomonas aeruginosa for the drug class is fetched from the database.","tool_type":"sc:SoftwareApplication"}}}