{"tool_name":"vardecrypt","contents":["biotools","bioschemas"],"fetched_metadata":{"biotools":{"id":"vardecrypt","home":"https://vardecrypt.com/app/vardecrypt","summary":"Novel and user-friendly tool to explore and prioritize variants in whole-exome sequencing data.","addition_date":"2024-01-22T10:40:00.589921Z","last_update_date":"2024-11-24T14:21:04.695493Z","tool_type":["Web application"]},"bioschemas":{"name":"VarDecrypt","home":"https://bio.tools/vardecrypt","summary":"Novel and user-friendly tool to explore and prioritize variants in whole-exome sequencing data.","tool_type":"sc:SoftwareApplication"}}}