{"tool_name":"xina","contents":["biotools","bioschemas"],"fetched_metadata":{"biotools":{"id":"xina","home":"https://www.bioconductor.org/packages/devel/bioc/html/XINA.html","license":"GPL-3.0","summary":"An R package for network analyses from multiplexed, time-resolved proteomics or trascriptomics data","addition_date":"2019-01-23T10:46:25Z","last_update_date":"2020-06-16T10:55:24Z","tool_type":["Library"],"version":["1.1.1"],"collections":["Bioconductor","Proteomics"]},"bioschemas":{"name":"XINA","home":"https://bio.tools/xina","license":"GPL-3.0","version":"1.1.1","summary":"An R package for network analyses from multiplexed, time-resolved proteomics or trascriptomics data","tool_type":"sc:SoftwareApplication"}}}